DNAv3_IntParser/__init__.py
DNAv3_IntParser-0.1.dev2.dist-info/LICENSE.txt
DNAv3_IntParser-0.1.dev2.dist-info/METADATA
DNAv3_IntParser-0.1.dev2.dist-info/WHEEL
DNAv3_IntParser-0.1.dev2.dist-info/top_level.txt
DNAv3_IntParser-0.1.dev2.dist-info/RECORD
