Metadata-Version: 2.1
Name: DNAv3-IntParser
Version: 0.1.dev2
Summary: a json parser for IOS XE router interfaces
Home-page: https://github.com/kriswans/
Author: Kris Swanson
Author-email: kriswans@cisco.com
License: MIT
Keywords: DNAv3,JSON,Cisco IOS-XE
Platform: UNKNOWN
Classifier: Development Status :: 3 - Alpha
Classifier: Intended Audience :: Developers
Classifier: Topic :: Software Development :: Build Tools
Classifier: License :: OSI Approved :: MIT License
Classifier: Programming Language :: Python :: 3.7
Requires-Python: >=3.5
